blue_krill/__init__.py
blue_krill/async_utils/__init__.py
blue_krill/async_utils/django_utils.py
blue_krill/async_utils/poll_task.py
blue_krill/auth/__init__.py
blue_krill/auth/client.py
blue_krill/auth/jwt.py
blue_krill/auth/utils.py
blue_krill/connections/__init__.py
blue_krill/connections/exceptions.py
blue_krill/connections/ha_algorithm.py
blue_krill/connections/ha_endpoint_pool.py
blue_krill/contextlib.py
blue_krill/cubing_case.py
blue_krill/data_types/__init__.py
blue_krill/data_types/enum.py
blue_krill/data_types/url.py
blue_krill/editions/__init__.py
blue_krill/editions/editionctl.py
blue_krill/encoding.py
blue_krill/encrypt/__init__.py
blue_krill/encrypt/handler.py
blue_krill/encrypt/legacy.py
blue_krill/encrypt/utils.py
blue_krill/models/__init__.py
blue_krill/models/fields.py
blue_krill/monitoring/__init__.py
blue_krill/monitoring/probe/__init__.py
blue_krill/monitoring/probe/base.py
blue_krill/monitoring/probe/exceptions.py
blue_krill/monitoring/probe/http.py
blue_krill/monitoring/probe/mysql.py
blue_krill/monitoring/probe/redis.py
blue_krill/monitoring/probe/tcp.py
blue_krill/monitoring/prometheus/__init__.py
blue_krill/monitoring/prometheus/django_utils.py
blue_krill/monitoring/prometheus/setups.py
blue_krill/py.typed
blue_krill/redis_tools/__init__.py
blue_krill/redis_tools/messaging.py
blue_krill/redis_tools/sentinel.py
blue_krill/secure/__init__.py
blue_krill/secure/bk_secure.py
blue_krill/secure/dj_environ.py
blue_krill/storages/__init__.py
blue_krill/storages/blobstore/__init__.py
blue_krill/storages/blobstore/base.py
blue_krill/storages/blobstore/bkrepo.py
blue_krill/storages/blobstore/exceptions.py
blue_krill/storages/blobstore/s3.py
blue_krill/termcolors.py
blue_krill/text.py
blue_krill/web/__init__.py
blue_krill/web/drf_utils.py
blue_krill/web/std_error.py
blue_krill-2.1.5.dist-info/METADATA
blue_krill-2.1.5.dist-info/WHEEL
blue_krill-2.1.5.dist-info/entry_points.txt
blue_krill-2.1.5.dist-info/RECORD
