Metadata-Version: 2.3
Name: blue-krill
Version: 2.1.5
Summary: Tools and common packages for blueking PaaS platform.
License: MIT
Author: blueking
Author-email: blueking@tencent.com
Requires-Python: >=3.9,<3.12
Classifier: License :: OSI Approved :: MIT License
Classifier: Programming Language :: Python :: 3
Classifier: Programming Language :: Python :: 3.9
Classifier: Programming Language :: Python :: 3.10
Classifier: Programming Language :: Python :: 3.11
Requires-Dist: bk-crypto-python-sdk (>=2.0.0,<3.0.0)
Requires-Dist: click
Requires-Dist: cryptography (>=3.0.0)
Requires-Dist: curlify (>=2.2.1,<3.0.0)
Requires-Dist: dataclasses (>=0.7) ; python_full_version >= "3.6.2" and python_version < "3.7"
Requires-Dist: django-environ (>=0.8.1)
Requires-Dist: pydantic
Requires-Dist: pyjwt (>=1.7.1)
Requires-Dist: python-editor (>=1.0.4,<2.0.0)
Requires-Dist: requests
Requires-Dist: six
Requires-Dist: toml
Requires-Dist: urllib3 (>=1.26.16,<2.0.0)
Requires-Dist: watchdog
Project-URL: Homepage, https://github.com/TencentBlueKing/bkpaas-python-sdk/
Project-URL: Repository, https://github.com/TencentBlueKing/bkpaas-python-sdk/
